sgsxmp/__init__.py
sgsxmp/sgsxmp.py
sgsxmp-1.1.0.dist-info/LICENSE
sgsxmp-1.1.0.dist-info/METADATA
sgsxmp-1.1.0.dist-info/WHEEL
sgsxmp-1.1.0.dist-info/entry_points.txt
sgsxmp-1.1.0.dist-info/top_level.txt
sgsxmp-1.1.0.dist-info/RECORD
