Metadata-Version: 2.1
Name: sgsxmp
Version: 1.1.0
Summary: Add xmp to Image Carriers
Home-page: UNKNOWN
Author: Andrew Neary
Author-email: andrew.neary@sgsco.com
License: SGS
Keywords: sgsxmp
Platform: UNKNOWN
Classifier: Programming Language :: Python :: 3
Classifier: Operating System :: OS Independent
License-File: LICENSE
Requires-Dist: python-xmp-toolkit (==2.0.1)
Requires-Dist: pytz (==2021.3)
